geodata/__init__.py
geodata/models.py
geodata/data/cities.json
geodata/data/countries+cities.json
geodata/data/countries+states+cities.json
geodata/data/countries+states.json
geodata/data/countries.json
geodata/data/regions.json
geodata/data/states+cities.json
geodata/data/states.json
geodata/data/subregions.json
geodata/management/__init__.py
geodata/management/commands/load_geodata.py
geodata/migrations/0001_initial.py
geodata/migrations/0002_alter_country_native.py
geodata/migrations/0003_alter_state_latitude_alter_state_longitude.py
geodata/migrations/__init__.py
geodata/tests/__init__.py
geodata/tests/test_models.py
django_geodata_mjomba-1.1.1.dist-info/METADATA
django_geodata_mjomba-1.1.1.dist-info/WHEEL
django_geodata_mjomba-1.1.1.dist-info/top_level.txt
django_geodata_mjomba-1.1.1.dist-info/RECORD
